html_writer/__init__.py
html_writer/_version.py
html_writer/html_writer.py
html_writer-1.1.1.dist-info/LICENSE
html_writer-1.1.1.dist-info/METADATA
html_writer-1.1.1.dist-info/WHEEL
html_writer-1.1.1.dist-info/top_level.txt
html_writer-1.1.1.dist-info/RECORD
