Metadata-Version: 2.1
Name: html-writer
Version: 1.1.1
Summary: A simple HTML writer
Home-page: https://github.com/KKawamura1/html_writer
Author: Keigo Kawamura
Author-email: kkawamura@logos.t.u-tokyo.ac.jp
License: UNKNOWN
Project-URL: Source, https://github.com/KKawamura1/html_writer
Keywords: HTML writer with markup simple
Platform: UNKNOWN
Classifier: Development Status :: 5 - Production/Stable
Classifier: Intended Audience :: Developers
Classifier: License :: OSI Approved :: MIT License
Classifier: Programming Language :: Python :: 3
Classifier: Programming Language :: Python :: 3.7
Classifier: Topic :: Software Development :: Libraries :: Python Modules
Classifier: Topic :: Text Processing :: Markup :: HTML
